rurage/__init__.py
rurage/config.py
rurage/ensemble.py
rurage/evaluator.py
rurage/metrics.py
rurage/report.py
rurage/tokenizer.py
RURAGE-1.1.1.dist-info/LICENSE
RURAGE-1.1.1.dist-info/METADATA
RURAGE-1.1.1.dist-info/WHEEL
RURAGE-1.1.1.dist-info/top_level.txt
RURAGE-1.1.1.dist-info/RECORD
