Metadata-Version: 2.1
Name: RURAGE
Version: 1.1.1
Summary: RURAGE (Robust Universal RAG Evaluation) is a Python library developed to speed-up evaluation of RAG systems with Correctness, Faithfulness and Relevance axes using a variety of deterministic and model-based metrics.
Author-email: Sidorov Ivan MTS AI <i.sidorov1@mts.ai>, Krayko Nikita MTS AI <n.kraiko@mts.ai>
Project-URL: Homepage, https://github.com/mts-ai/rurage
Classifier: Programming Language :: Python :: 3
Classifier: License :: OSI Approved :: MIT License
Classifier: Operating System :: OS Independent
Requires-Python: >=3.6
License-File: LICENSE
Requires-Dist: pandas
Requires-Dist: numpy
Requires-Dist: scikit-learn
Requires-Dist: nltk
Requires-Dist: pymorphy2
Requires-Dist: rouge-score
Requires-Dist: transformers
Requires-Dist: torch
Requires-Dist: tqdm
Requires-Dist: catboost
